gvsbuild/__init__.py
gvsbuild/build.py
gvsbuild/deps.py
gvsbuild/groups.py
gvsbuild/list.py
gvsbuild/main.py
gvsbuild/outdated.py
gvsbuild/tools.py
gvsbuild/patches/mod.md
gvsbuild/patches/stack.props
gvsbuild/patches/adwaita-icon-theme/001-fix-svg-symlink.patch
gvsbuild/patches/check-libs/COPYING
gvsbuild/patches/check-libs/check_utils.c
gvsbuild/patches/check-libs/check_utils.h
gvsbuild/patches/check-libs/meson.build
gvsbuild/patches/check-libs/test_atk.c
gvsbuild/patches/check-libs/test_cairo.c
gvsbuild/patches/check-libs/test_freetype2.c
gvsbuild/patches/check-libs/test_gdk-pixbuf.c
gvsbuild/patches/check-libs/test_glib.c
gvsbuild/patches/check-libs/test_jasper.c
gvsbuild/patches/check-libs/test_json_glib.c
gvsbuild/patches/check-libs/test_libarchive.c
gvsbuild/patches/check-libs/test_libcurl.c
gvsbuild/patches/check-libs/test_libffi.c
gvsbuild/patches/check-libs/test_libjpeg-turbo.c
gvsbuild/patches/check-libs/test_libjpeg.c
gvsbuild/patches/check-libs/test_libpng.c
gvsbuild/patches/check-libs/test_libtiff-4.c
gvsbuild/patches/check-libs/test_libxml2.c
gvsbuild/patches/check-libs/test_libyuv.c
gvsbuild/patches/check-libs/test_pango.c
gvsbuild/patches/check-libs/test_wing.c
gvsbuild/patches/check-libs/test_zlib.c
gvsbuild/patches/clutter/build/win32/vs12/Makefile.am
gvsbuild/patches/clutter/build/win32/vs12/Makefile.in
gvsbuild/patches/clutter/build/win32/vs12/README.txt
gvsbuild/patches/clutter/build/win32/vs12/cally-atkcomponent-example.vcxproj
gvsbuild/patches/clutter/build/win32/vs12/cally-atkcomponent-example.vcxproj.filters
gvsbuild/patches/clutter/build/win32/vs12/cally-atkeditabletext-example.vcxproj
gvsbuild/patches/clutter/build/win32/vs12/cally-atkeditabletext-example.vcxproj.filters
gvsbuild/patches/clutter/build/win32/vs12/cally-atkevents-example.vcxproj
gvsbuild/patches/clutter/build/win32/vs12/cally-atkevents-example.vcxproj.filters
gvsbuild/patches/clutter/build/win32/vs12/cally-atktext-example.vcxproj
gvsbuild-2026.1.0.dist-info/METADATA
gvsbuild-2026.1.0.dist-info/WHEEL
gvsbuild-2026.1.0.dist-info/entry_points.txt
gvsbuild-2026.1.0.dist-info/licenses/AUTHORS.md
gvsbuild-2026.1.0.dist-info/licenses/COPYING
gvsbuild-2026.1.0.dist-info/RECORD
