Metadata-Version: 2.4
Name: gvsbuild
Version: 2026.1.0
Summary: GTK stack for Windows
Author-email: Ignacio Casal Quinteiro <qignacio@amazon.com>, Dan Yeaw <dan@yeaw.me>
License:                     GNU GENERAL PUBLIC LICENSE
License-File: AUTHORS.md
License-File: COPYING
Classifier: Development Status :: 5 - Production/Stable
Classifier: Environment :: X11 Applications :: GTK
Classifier: Operating System :: Microsoft :: Windows
Classifier: Topic :: Software Development :: Build Tools
Requires-Python: !=3.13.4,<4.0,>=3.10
Requires-Dist: build>=1.3.0
Requires-Dist: cyclopts>=4.0.0b2
Requires-Dist: pip
Requires-Dist: setuptools>=69.2; python_version >= '3.12'
Provides-Extra: outdated
Requires-Dist: lastversion<4.0.0,>=2.4.2; extra == 'outdated'
Requires-Dist: packaging>=25.0; extra == 'outdated'
